{
  "db_name": "SQLite",
  "query": "\n            SELECT\n                id AS \"id: Uuid\",\n                project_id  AS \"project_id: Uuid\",\n                name\n            FROM branches\n            WHERE project_id = ?\n            ",
  "describe": {
    "columns": [
      {
        "name": "id: Uuid",
        "ordinal": 0,
        "type_info": "Blob"
      },
      {
        "name": "project_id: Uuid",
        "ordinal": 1,
        "type_info": "Blob"
      },
      {
        "name": "name",
        "ordinal": 2,
        "type_info": "Text"
      }
    ],
    "parameters": {
      "Right": 1
    },
    "nullable": [
      false,
      false,
      false
    ]
  },
  "hash": "5e4f9e482fcb766c32e9f5013cfb28af95883080454c13ca4c23599697647d4d"
}
